fanceai_types/__init__.py
fanceai_types/common.py
fanceai_types-0.1.0.dist-info/licenses/LICENSE
fanceai_types-0.1.0.dist-info/METADATA
fanceai_types-0.1.0.dist-info/WHEEL
fanceai_types-0.1.0.dist-info/top_level.txt
fanceai_types-0.1.0.dist-info/RECORD
