Metadata-Version: 2.4
Name: fanceai_types
Version: 0.1.0
Summary: 定义通用数据结构和接口的 Python 包，适用于数据处理、算法、后端等模块间共享
Author: lihua, xi
License: MIT License
Classifier: Programming Language :: Python :: 3
Classifier: License :: OSI Approved :: MIT License
Classifier: Operating System :: OS Independent
Requires-Python: >=3.8
License-File: LICENSE
Requires-Dist: pydantic>=2.0
Dynamic: license-file
